{
  "hash": "19313775",
  "configHash": "2e48f105",
  "lockfileHash": "9955243b",
  "browserHash": "8cec084f",
  "optimized": {
    "react-dom": {
      "src": "../../node_modules/react-dom/index.js",
      "file": "react-dom.js",
      "fileHash": "1fb87ee3",
      "needsInterop": true
    },
    "react-dom/client": {
      "src": "../../node_modules/react-dom/client.js",
      "file": "react-dom_client.js",
      "fileHash": "64df406d",
      "needsInterop": true
    },
    "react": {
      "src": "../../node_modules/react/index.js",
      "file": "react.js",
      "fileHash": "7d92bc8d",
      "needsInterop": true
    },
    "react/jsx-dev-runtime": {
      "src": "../../node_modules/react/jsx-dev-runtime.js",
      "file": "react_jsx-dev-runtime.js",
      "fileHash": "3d07d3dd",
      "needsInterop": true
    }
  },
  "chunks": {
    "react-Na5-BvaJ": {
      "file": "react-Na5-BvaJ.js",
      "isDynamicEntry": false
    }
  }
}